ignite/__init__.py
ignite/__version__.py
ignite/ds_utils/__init__.py
ignite/ds_utils/evaluation/__init__.py
ignite/ds_utils/evaluation/evaluate.py
ignite/ds_utils/evaluation/metrics.py
ignite/ds_utils/exploration/__init__.py
ignite/ds_utils/exploration/explore.py
ignite/ds_utils/modeling/__init__.py
ignite/logging/__init__.py
ignite/logging/base.py
ignite/logging/escape_codes.py
ignite/logging/logger.py
ignite/logging/logging_formatter.py
ignite/mlflow/__init__.py
ignite/mlflow/mlflow_wrapper.py
ignite/s3/__init__.py
ignite/s3/s3.py
ignite/snowflake/__init__.py
ignite/spark/__init__.py
ignite/spark/spark.py
lp_ignite-0.0.1.dist-info/METADATA
lp_ignite-0.0.1.dist-info/WHEEL
lp_ignite-0.0.1.dist-info/top_level.txt
lp_ignite-0.0.1.dist-info/RECORD
