Metadata-Version: 2.1
Name: lp-ignite
Version: 0.0.1
Summary: Ignite - High-Level utilities library for various tools such as Spark, SnowFlake, MLflow 
Home-page: https://gitlab.leaseplan.io/data/data-science/ignite
Author: LeasePlan AI Engineering Team
Keywords: spark,mlflow,boto3,logger,cicd,sagemaker,snowflake
Platform: any
Classifier: Programming Language :: Python
Classifier: Development Status :: 4 - Beta
Classifier: Intended Audience :: Developers
Classifier: Topic :: System :: Logging
Classifier: Topic :: Software Development :: Libraries :: Python Modules
Requires-Python: >=3.7
Requires-Dist: pyyaml
Requires-Dist: scikit-learn (==1.0.2)
Requires-Dist: pandas
Requires-Dist: boto3
Requires-Dist: moto
Requires-Dist: pytest
Requires-Dist: matplotlib
Requires-Dist: coverage (==6.4.1)
Requires-Dist: seaborn (==0.11.2)
Requires-Dist: mlflow (==1.27.0)
